{"options":{"validator":{"$jsonSchema":{"bsonType":"object","required":["_id","serial_number","casts"],"properties":{"_id":{"bsonType":"objectId","description":"Unique identifier for the machine (required)."},"serial_number":{"bsonType":"string","description":"Serial number of the machine (required)."},"casts":{"bsonType":"array","description":"Array of votes casted in the machine.","items":{"bsonType":"object","required":["candidate"],"properties":{"candidate":{"bsonType":"objectId","description":"Candidate voted (required)."}}}}}}}},"indexes":[{"v":{"$numberInt":"2"},"key":{"_id":{"$numberInt":"1"}},"name":"_id_"},{"v":{"$numberInt":"2"},"key":{"serial_number":{"$numberInt":"1"}},"name":"serial_number_1","unique":true}],"uuid":"3958d313909844ac90dfa091af7eacdb","collectionName":"machines","type":"collection"}